dycord/__init__.py
dycord/blacklist.py
dycord/bot.py
dycord/components.py
dycord/emb.py
dycord/enums.py
dycord/errors.py
dycord/logs.py
dycord/sql.py
dycord/times.py
dycord/utils.py
dycord/cogs/blacklist.py
dycord/cogs/help.py
dycord/cogs/status_changer.py
dycord/cogs/dpy/blacklist_setup.py
dycord/cogs/dpy/help_setup.py
dycord/cogs/dpy/status_changer_setup.py
dycord/cogs/pyc/blacklist_setup.py
dycord/cogs/pyc/help_setup.py
dycord/cogs/pyc/status_changer_setup.py
dycord/internal/__init__.py
dycord/internal/colors.py
dycord/internal/config.py
dycord/internal/embed_templates.py
dycord/internal/ready_style.py
dycord/internal/translation.py
dycord/internal/dc/__init__.py
dycord/internal/dc/dc_imports.py
dycord/internal/language/de.json
dycord/internal/language/en.json
dycord/internal/language/languages.py
dycord-0.5.2.dist-info/LICENSE
dycord-0.5.2.dist-info/METADATA
dycord-0.5.2.dist-info/WHEEL
dycord-0.5.2.dist-info/top_level.txt
dycord-0.5.2.dist-info/RECORD
